LICENSE.txt
MANIFEST.in
README.rst
setup.cfg
setup.py
djangocms_layouter.egg-info/PKG-INFO
djangocms_layouter.egg-info/SOURCES.txt
djangocms_layouter.egg-info/dependency_links.txt
djangocms_layouter.egg-info/not-zip-safe
djangocms_layouter.egg-info/requires.txt
djangocms_layouter.egg-info/top_level.txt
layouter/__init__.py
layouter/apps.py
layouter/cms_plugins.py
layouter/cms_toolbars.py
layouter/forms.py
layouter/models.py
layouter/urls.py
layouter/views.py
layouter/migrations/.DS_Store
layouter/migrations/0001_initial.py
layouter/migrations/0002_equal_height.py
layouter/migrations/0003_auto_20190129_1002.py
layouter/migrations/0004_background_options.py
layouter/migrations/0005_auto_20200428_1143.py
layouter/migrations/__init__.py
layouter/migrations/__init__.pyc
layouter/static/layouter/css/bootstrap.min.css
layouter/static/layouter/css/layouter.css
layouter/static/layouter/fonts/layouter.eot
layouter/static/layouter/fonts/layouter.svg
layouter/static/layouter/fonts/layouter.ttf
layouter/static/layouter/fonts/layouter.woff
layouter/static/layouter/js/layouter.js
layouter/static/layouter/js/parallax.min.js
layouter/templates/layouter/change_form.html
layouter/templates/layouter/radio_option.html
layouter/templates/layouter/bootstrap3/container.html
layouter/templates/layouter/bootstrap3/partials/four_cols.html
layouter/templates/layouter/bootstrap3/partials/one_col.html
layouter/templates/layouter/bootstrap3/partials/three_cols.html
layouter/templates/layouter/bootstrap3/partials/two_cols.html
layouter/templates/layouter/bootstrap4/container.html
layouter/templates/layouter/bootstrap4/partials/four_cols.html
layouter/templates/layouter/bootstrap4/partials/one_col.html
layouter/templates/layouter/bootstrap4/partials/three_cols.html
layouter/templates/layouter/bootstrap4/partials/two_cols.html
layouter/templates/layouter/partials/layouter_javascript.html