Metadata-Version: 1.1
Name: djangocms-layouter
Version: 1.0.0
Summary: Grid system for Django-CMS users which aims for ease of use.
Home-page: https://github.com/Blueshoe/djangocms-layouter
Author: Robert Stein
Author-email: robert@blueshoe.de
License: MIT
Download-URL: https://github.com/Blueshoe/djangocms-layouter/archive/1.0.0.zip
Keywords: django,Django CMS,grid,bootstrap,website,CMS,Blueshoe
Platform: UNKNOWN
Classifier: Framework :: Django
Classifier: Environment :: Web Environment
Classifier: Intended Audience :: Developers
Classifier: Operating System :: OS Independent
Classifier: Programming Language :: Python
Classifier: Programming Language :: Python :: 3
Classifier: Programming Language :: Python :: 3.4
Classifier: Programming Language :: Python :: 3.5
Classifier: Programming Language :: Python :: 3.6
Classifier: Programming Language :: Python :: 3.7
Classifier: Topic :: Internet :: WWW/HTTP
Classifier: Topic :: Internet :: WWW/HTTP :: Dynamic Content
Classifier: Topic :: Software Development :: Libraries :: Python Modules
Classifier: Topic :: Software Development :: Libraries :: Application Frameworks
